{"people":[{"_id":"huaweihuang","企微ID":"huaweihuang","中文名":"黄华伟","身份证姓名":"黄华伟","性别":"男","部门/中心":"数据中心","常驻城市":"深圳","有无驾照":"是","开车意愿":"非常可以","带无人机":"木有无人机...","手机号":"","身份证号":"","去程航班":"广州8号出发-- CZ3477广州白云-林芝米林(07:05-11:00)","返程航班":"深圳11号到达-- TV9984林芝米林-重庆江北(11:20-13:35) + CZ3456重庆江北-深圳宝安(15:35-17:55)","室友意向":"Tomtang","车号":"2号车","游戏分组":"1","现场角色":"","重庆住宿(11.7)":"","索松村住宿(11.8)":"索松村桃花韵酒店 17号 全景双床4（室友：唐韬）","巴松措住宿(11.9~10)":"巴松措纳拉尕布民宿 17号 二楼双床房（室友：唐韬）","饮食忌口/过敏":"","高反情况":"","打呼噜":"","其他备注":""},{"_id":"sogu","企微ID":"sogu","中文名":"古开元","身份证姓名":"古开元","性别":"男","部门/中心":"运营平台部","常驻城市":"","有无驾照":"是","开车意愿":"非常可以","带无人机":"木有无人机...","手机号":"","身份证号":"","去程航班":"广州8号出发-- CZ3477广州白云-林芝米林(07:05-11:00)","返程航班":"深圳11号到达-- TV9984林芝米林-重庆江北(11:20-13:35) + CZ3456重庆江北-深圳宝安(15:35-17:55)","室友意向":"无，随缘","车号":"2号车","游戏分组":"1","现场角色":"","重庆住宿(11.7)":"","索松村住宿(11.8)":"索松村桃花韵酒店 19号 正对大床（单人）","巴松措住宿(11.9~10)":"巴松措纳拉尕布民宿 19号 二楼大床房（单人）","饮食忌口/过敏":"","高反情况":"","打呼噜":"","其他备注":""},{"_id":"chenzzchen","企微ID":"chenzzchen","中文名":"陈壮志","身份证姓名":"陈壮志","性别":"男","部门/中心":"云平台技术运营中心","常驻城市":"","有无驾照":"是","开车意愿":"我可以做替补","带无人机":"木有无人机...","手机号":"","身份证号":"","去程航班":"北京7号出发-- CA1449北京首都-重庆江北(18:45-22:05) + TV9983重庆江北-林芝米林(07:50-10:30)","返程航班":"北京首都11号到达-- TV9984林芝米林-重庆江北(11:20-13:35) + CA1438 重庆江北-北京首都(15:55-18:30)","室友意向":"无","车号":"2号车","游戏分组":"1","现场角色":"","重庆住宿(11.7)":"重庆诺富特酒店 1号（室友：周啟彬）","索松村住宿(11.8)":"索松村桃花韵酒店 3号 正对双床3（室友：李方源）","巴松措住宿(11.9~10)":"巴松措纳拉尕布民宿 3号 三楼双床房（室友：李方源）","饮食忌口/过敏":"","高反情况":"","打呼噜":"","其他备注":"打呼噜比较严重，希望对室友影响小一些"},{"_id":"chaselli","企微ID":"chaselli","中文名":"李琛","身份证姓名":"李琛","性别":"男","部门/中心":"多媒体技术中心","常驻城市":"深圳","有无驾照":"否","开车意愿":"还是算了吧","带无人机":"木有无人机...","手机号":"","身份证号":"","去程航班":"北京7号出发-- CA1449北京首都-重庆江北(18:45-22:05) + TV9983重庆江北-林芝米林(07:50-10:30)","返程航班":"深圳11号到达-- TV9984林芝米林-重庆江北(11:20-13:35) + CZ3456重庆江北-深圳宝安(15:35-17:55)","室友意向":"无","车号":"2号车","游戏分组":"1","现场角色":"","重庆住宿(11.7)":"重庆诺富特酒店 3号（室友：马子扬）","索松村住宿(11.8)":"索松村桃花韵酒店 7号 正对双床7（室友：赵自翔）","巴松措住宿(11.9~10)":"巴松措纳拉尕布民宿 7号 三楼双床房（室友：赵自翔）","饮食忌口/过敏":"","高反情况":"","打呼噜":"","其他备注":""},{"_id":"joeyye","企微ID":"joeyye","中文名":"叶泽雄","身份证姓名":"叶泽雄","性别":"男","部门/中心":"信息二组","常驻城市":"","有无驾照":"是","开车意愿":"非常可以","带无人机":"木有无人机...","手机号":"","身份证号":"","去程航班":"广州8号出发-- CZ3477广州白云-林芝米林(07:05-11:00)","返程航班":"深圳11号到达-- TV9984林芝米林-重庆江北(11:20-13:35) + CZ3456重庆江北-深圳宝安(15:35-17:55)","室友意向":"wanpengxiao","车号":"3号车","游戏分组":"1","现场角色":"","重庆住宿(11.7)":"","索松村住宿(11.8)":"索松村桃花韵酒店 15号 全景双床2（室友：胡博杰）","巴松措住宿(11.9~10)":"巴松措纳拉尕布民宿 15号 二楼双床房（室友：胡博杰）","饮食忌口/过敏":"","高反情况":"","打呼噜":"","其他备注":""},{"_id":"nobleqiao","企微ID":"nobleqiao","中文名":"乔宁博","身份证姓名":"乔宁博","性别":"男","部门/中心":"多媒体技术中心","常驻城市":"深圳","有无驾照":"是","开车意愿":"非常可以","带无人机":"木有无人机...","手机号":"","身份证号":"","去程航班":"深圳7号出发-- ZH9469深圳宝安-重庆江北(20:15-22:40) + TV9983重庆江北-林芝米林(07:50-10:30)","返程航班":"深圳11号到达-- TV9984林芝米林-重庆江北(11:20-13:35) + CZ3456重庆江北-深圳宝安(15:35-17:55)","室友意向":"sidneyzhou","车号":"3号车","游戏分组":"1","现场角色":"","重庆住宿(11.7)":"重庆诺富特酒店 5号（室友：陈培炫）","索松村住宿(11.8)":"索松村桃花韵酒店 11号 正对双床11（室友：周煜）","巴松措住宿(11.9~10)":"巴松措纳拉尕布民宿 11号 二楼双床房（室友：周煜）","饮食忌口/过敏":"","高反情况":"","打呼噜":"","其他备注":""},{"_id":"yuetangdeng","企微ID":"yuetangdeng","中文名":"邓月堂","身份证姓名":"邓月堂","性别":"男","部门/中心":"测试中心","常驻城市":"广州","有无驾照":"是","开车意愿":"我可以做替补","带无人机":"木有无人机...","手机号":"","身份证号":"","去程航班":"广州8号出发-- CZ3477广州白云-林芝米林(07:05-11:00)","返程航班":"广州11号到达-- CZ3478林芝米林-广州白云(11:40-15:20)","室友意向":"无","车号":"3号车","游戏分组":"1","现场角色":"","重庆住宿(11.7)":"","索松村住宿(11.8)":"索松村桃花韵酒店 9号 正对双床9（室友：郑吴杰）","巴松措住宿(11.9~10)":"巴松措纳拉尕布民宿 9号 三楼双床房（室友：郑吴杰）","饮食忌口/过敏":"","高反情况":"","打呼噜":"","其他备注":""},{"_id":"wujiezheng","企微ID":"wujiezheng","中文名":"郑吴杰","身份证姓名":"郑吴杰","性别":"男","部门/中心":"测试中心","常驻城市":"深圳","有无驾照":"是","开车意愿":"我可以做替补","带无人机":"木有无人机...","手机号":"","身份证号":"","去程航班":"广州8号出发-- CZ3477广州白云-林芝米林(07:05-11:00)","返程航班":"广州11号到达-- CZ3478林芝米林-广州白云(11:40-15:20)","室友意向":"无","车号":"3号车","游戏分组":"1","现场角色":"","重庆住宿(11.7)":"","索松村住宿(11.8)":"索松村桃花韵酒店 9号 正对双床9（室友：邓月堂）","巴松措住宿(11.9~10)":"巴松措纳拉尕布民宿 9号 三楼双床房（室友：邓月堂）","饮食忌口/过敏":"","高反情况":"","打呼噜":"","其他备注":""},{"_id":"mattzheng","企微ID":"mattzheng","中文名":"郑海兵","身份证姓名":"郑海兵","性别":"男","部门/中心":"质量平台组","常驻城市":"","有无驾照":"是","开车意愿":"非常可以","带无人机":"木有无人机...","手机号":"","身份证号":"","去程航班":"广州8号出发-- CZ3477广州白云-林芝米林(07:05-11:00)","返程航班":"广州11号到达-- CZ3478林芝米林-广州白云(11:40-15:20)","室友意向":"frankxia","车号":"5号车","游戏分组":"2","现场角色":"","重庆住宿(11.7)":"","索松村住宿(11.8)":"索松村桃花韵酒店 4号 正对双床4（室友：夏凡）","巴松措住宿(11.9~10)":"巴松措纳拉尕布民宿 4号 三楼双床房（室友：夏凡）","饮食忌口/过敏":"","高反情况":"","打呼噜":"","其他备注":""},{"_id":"drakezhang","企微ID":"drakezhang","中文名":"张鼓华","身份证姓名":"张鼓华","性别":"男","部门/中心":"模式识别中心","常驻城市":"北京","有无驾照":"是","开车意愿":"非常可以","带无人机":"带了无人机，不过是个穿越机","手机号":"","身份证号":"","去程航班":"北京7号出发-- CA1449北京首都-重庆江北(18:45-22:05) + TV9983重庆江北-林芝米林(07:50-10:30)","返程航班":"北京首都11号到达-- TV9984林芝米林-重庆江北(11:20-13:35) + CA1438 重庆江北-北京首都(15:55-18:30)","室友意向":"fandongmeng","车号":"5号车","游戏分组":"2","现场角色":"","重庆住宿(11.7)":"重庆诺富特酒店 2号（室友：孟凡东）","索松村住宿(11.8)":"索松村桃花韵酒店 18号 庭院双床1（室友：孟凡东）","巴松措住宿(11.9~10)":"巴松措纳拉尕布民宿 18号 二楼双床房（室友：孟凡东）","饮食忌口/过敏":"","高反情况":"","打呼噜":"","其他备注":""},{"_id":"biliypang","企微ID":"biliypang","中文名":"庞永杰","身份证姓名":"庞永杰","性别":"男","部门/中心":"信息中心","常驻城市":"","有无驾照":"是","开车意愿":"我可以做替补","带无人机":"我带~","手机号":"","身份证号":"","去程航班":"深圳7号出发-- ZH9469深圳宝安-重庆江北(20:15-22:40) + TV9983重庆江北-林芝米林(07:50-10:30)","返程航班":"深圳11号到达-- TV9984林芝米林-重庆江北(11:20-13:35) + CZ3456重庆江北-深圳宝安(15:35-17:55)","室友意向":"无","车号":"5号车","游戏分组":"2","现场角色":"","重庆住宿(11.7)":"重庆诺富特酒店 4号（室友：胡博杰）","索松村住宿(11.8)":"索松村桃花韵酒店 12号 正对双床12（室友：文杰）","巴松措住宿(11.9~10)":"巴松措纳拉尕布民宿 12号 二楼双床房（室友：文杰）","饮食忌口/过敏":"","高反情况":"","打呼噜":"","其他备注":""},{"_id":"iotazhang","企微ID":"iotazhang","中文名":"张文瑞","身份证姓名":"张文瑞","性别":"男","部门/中心":"后台开发中心","常驻城市":"广州","有无驾照":"是","开车意愿":"还是算了吧","带无人机":"木有无人机...","手机号":"","身份证号":"","去程航班":"广州8号出发-- CZ3477广州白云-林芝米林(07:05-11:00)","返程航班":"广州11号到达-- CZ3478林芝米林-广州白云(11:40-15:20)","室友意向":"无","车号":"5号车","游戏分组":"2","现场角色":"","重庆住宿(11.7)":"","索松村住宿(11.8)":"索松村桃花韵酒店 8号 正对双床8（室友：邓锦福）","巴松措住宿(11.9~10)":"巴松措纳拉尕布民宿 8号 三楼双床房（室友：邓锦福）","饮食忌口/过敏":"","高反情况":"","打呼噜":"","其他备注":""},{"_id":"bierhuang","企微ID":"bierhuang","中文名":"黄清","身份证姓名":"黄清","性别":"男","部门/中心":"后台开发中心","常驻城市":"广州","有无驾照":"是","开车意愿":"非常可以","带无人机":"木有无人机...","手机号":"","身份证号":"","去程航班":"广州8号出发-- CZ3477广州白云-林芝米林(07:05-11:00)","返程航班":"广州11号到达-- CZ3478林芝米林-广州白云(11:40-15:20)","室友意向":"sarlmolchen","车号":"6号车","游戏分组":"2","现场角色":"","重庆住宿(11.7)":"","索松村住宿(11.8)":"索松村桃花韵酒店 6号 正对双床6（室友：陈国敏）","巴松措住宿(11.9~10)":"巴松措纳拉尕布民宿 6号 三楼双床房（室友：陈国敏）","饮食忌口/过敏":"","高反情况":"","打呼噜":"","其他备注":""},{"_id":"flashlin","企微ID":"flashlin","中文名":"林枫","身份证姓名":"林枫","性别":"男","部门/中心":"基础架构中心","常驻城市":"广州","有无驾照":"是","开车意愿":"我可以做替补","带无人机":"可带，但不太会","手机号":"","身份证号":"","去程航班":"广州8号出发-- CZ3477广州白云-林芝米林(07:05-11:00)","返程航班":"广州11号到达-- CZ3478林芝米林-广州白云(11:40-15:20)","室友意向":"rockzheng","车号":"6号车","游戏分组":"2","现场角色":"","重庆住宿(11.7)":"","索松村住宿(11.8)":"索松村桃花韵酒店 16号 全景双床3（室友：郑建军）","巴松措住宿(11.9~10)":"巴松措纳拉尕布民宿 16号 二楼双床房（室友：郑建军）","饮食忌口/过敏":"","高反情况":"","打呼噜":"","其他备注":""},{"_id":"jackliang","企微ID":"jackliang","中文名":"梁焯佳","身份证姓名":"梁焯佳","性别":"男","部门/中心":"业务中心","常驻城市":"","有无驾照":"是","开车意愿":"还是算了吧","带无人机":"木有无人机...","手机号":"","身份证号":"","去程航班":"广州8号出发-- CZ3477广州白云-林芝米林(07:05-11:00)","返程航班":"广州11号到达-- CZ3478林芝米林-广州白云(11:40-15:20)","室友意向":"elonqi","车号":"6号车","游戏分组":"2","现场角色":"","重庆住宿(11.7)":"","索松村住宿(11.8)":"索松村桃花韵酒店 13号 正对双床13（室友：祁麟）","巴松措住宿(11.9~10)":"巴松措纳拉尕布民宿 13号 二楼双床房（室友：祁麟）","饮食忌口/过敏":"","高反情况":"","打呼噜":"","其他备注":""},{"_id":"tomtang","企微ID":"tomtang","中文名":"唐韬","身份证姓名":"唐韬","性别":"男","部门/中心":"机器学习平台中心","常驻城市":"广州","有无驾照":"","开车意愿":"","带无人机":"","手机号":"","身份证号":"","去程航班":"广州8号出发-- CZ3477广州白云-林芝米林(07:05-11:00)","返程航班":"广州11号到达-- CZ3478林芝米林-广州白云(11:40-15:20)","室友意向":"huaweihuang","车号":"6号车","游戏分组":"2","现场角色":"","重庆住宿(11.7)":"","索松村住宿(11.8)":"索松村桃花韵酒店 17号 全景双床4（室友：黄华伟）","巴松措住宿(11.9~10)":"巴松措纳拉尕布民宿 17号 二楼双床房（室友：黄华伟）","饮食忌口/过敏":"","高反情况":"","打呼噜":"","其他备注":""},{"_id":"ziyangma","企微ID":"ziyangma","中文名":"马子扬","身份证姓名":"马子扬","性别":"男","部门/中心":"多媒体技术中心","常驻城市":"深圳","有无驾照":"是","开车意愿":"非常可以","带无人机":"木有无人机...","手机号":"","身份证号":"","去程航班":"北京7号出发-- CA1449北京首都-重庆江北(18:45-22:05) + TV9983重庆江北-林芝米林(07:50-10:30)","返程航班":"10号返程。川航U8030到重庆转CZ8816到北京，感谢","室友意向":"fengyunrao","车号":"7号车","游戏分组":"3","现场角色":"","重庆住宿(11.7)":"重庆诺富特酒店 3号（室友：李琛）","索松村住宿(11.8)":"索松村桃花韵酒店 14号 全景双床1（室友：饶峰云）","巴松措住宿(11.9~10)":"巴松措纳拉尕布民宿 14号 二楼双床房（室友：饶峰云）","饮食忌口/过敏":"","高反情况":"","打呼噜":"","其他备注":""},{"_id":"fandongmeng","企微ID":"fandongmeng","中文名":"孟凡东","身份证姓名":"孟凡东","性别":"男","部门/中心":"基础技术二组","常驻城市":"","有无驾照":"是","开车意愿":"非常可以","带无人机":"我带~","手机号":"","身份证号":"","去程航班":"北京7号出发-- CA1449北京首都-重庆江北(18:45-22:05) + TV9983重庆江北-林芝米林(07:50-10:30)","返程航班":"北京首都11号到达-- TV9984林芝米林-重庆江北(11:20-13:35) + CA1438 重庆江北-北京首都(15:55-18:30)","室友意向":"drakezhang","车号":"7号车","游戏分组":"3","现场角色":"","重庆住宿(11.7)":"重庆诺富特酒店 2号（室友：张鼓华）","索松村住宿(11.8)":"索松村桃花韵酒店 18号 庭院双床1（室友：张鼓华）","巴松措住宿(11.9~10)":"巴松措纳拉尕布民宿 18号 二楼双床房（室友：张鼓华）","饮食忌口/过敏":"","高反情况":"","打呼噜":"","其他备注":""},{"_id":"austindeng","企微ID":"austindeng","中文名":"邓锦福","身份证姓名":"邓锦福","性别":"男","部门/中心":"后台开发中心","常驻城市":"广州","有无驾照":"是","开车意愿":"我可以做替补","带无人机":"木有无人机...","手机号":"","身份证号":"","去程航班":"广州8号出发-- CZ3477广州白云-林芝米林(07:05-11:00)","返程航班":"广州11号到达-- CZ3478林芝米林-广州白云(11:40-15:20)","室友意向":"无","车号":"7号车","游戏分组":"3","现场角色":"","重庆住宿(11.7)":"","索松村住宿(11.8)":"索松村桃花韵酒店 8号 正对双床8（室友：张文瑞）","巴松措住宿(11.9~10)":"巴松措纳拉尕布民宿 8号 三楼双床房（室友：张文瑞）","饮食忌口/过敏":"","高反情况":"","打呼噜":"","其他备注":"室友最好不打呼噜"},{"_id":"qibinzhou","企微ID":"qibinzhou","中文名":"周啟彬","身份证姓名":"周啟彬","性别":"男","部门/中心":"云平台技术运营中心","常驻城市":"深圳","有无驾照":"是","开车意愿":"我可以做替补","带无人机":"木有无人机...","手机号":"","身份证号":"","去程航班":"深圳7号出发-- ZH9469深圳宝安-重庆江北(20:15-22:40) + TV9983重庆江北-林芝米林(07:50-10:30)","返程航班":"广州11号到达-- CZ3478林芝米林-广州白云(11:40-15:20)","室友意向":"无，随机分配位靓仔（靓女也行）","车号":"7号车","游戏分组":"3","现场角色":"","重庆住宿(11.7)":"重庆诺富特酒店 1号（室友：陈壮志）","索松村住宿(11.8)":"索松村桃花韵酒店 5号 正对双床5（室友：林子皓）","巴松措住宿(11.9~10)":"巴松措纳拉尕布民宿 5号 三楼双床房（室友：林子皓）","饮食忌口/过敏":"","高反情况":"","打呼噜":"","其他备注":""},{"_id":"welkinwen","企微ID":"welkinwen","中文名":"文杰","身份证姓名":"文杰","性别":"男","部门/中心":"机器学习平台中心","常驻城市":"深圳","有无驾照":"是","开车意愿":"非常可以","带无人机":"我带~","手机号":"","身份证号":"","去程航班":"深圳7号出发-- ZH9469深圳宝安-重庆江北(20:15-22:40) + TV9983重庆江北-林芝米林(07:50-10:30)","返程航班":"深圳11号到达-- TV9984林芝米林-重庆江北(11:20-13:35) + CZ3456重庆江北-深圳宝安(15:35-17:55)","室友意向":"无","车号":"8号车","游戏分组":"3","现场角色":"","重庆住宿(11.7)":"重庆诺富特酒店 6号（室友：周煜）","索松村住宿(11.8)":"索松村桃花韵酒店 12号 正对双床12（室友：庞永杰）","巴松措住宿(11.9~10)":"巴松措纳拉尕布民宿 12号 二楼双床房（室友：庞永杰）","饮食忌口/过敏":"","高反情况":"","打呼噜":"","其他备注":""},{"_id":"paulohuang","企微ID":"paulohuang","中文名":"黄皖湘","身份证姓名":"黄皖湘","性别":"男","部门/中心":"接入组","常驻城市":"","有无驾照":"是","开车意愿":"我可以做替补","带无人机":"木有无人机...","手机号":"","身份证号":"","去程航班":"广州8号出发-- CZ3477广州白云-林芝米林(07:05-11:00)","返程航班":"广州11号到达-- CZ3478林芝米林-广州白云(11:40-15:20)","室友意向":"fieldsxie","车号":"8号车","游戏分组":"3","现场角色":"","重庆住宿(11.7)":"","索松村住宿(11.8)":"索松村桃花韵酒店 10号 正对双床10（室友：陈培炫）","巴松措住宿(11.9~10)":"巴松措纳拉尕布民宿 10号 二楼双床房（室友：陈培炫）","饮食忌口/过敏":"","高反情况":"","打呼噜":"","其他备注":""},{"_id":"funnylin","企微ID":"funnylin","中文名":"林子皓","身份证姓名":"林子皓","性别":"男","部门/中心":"云平台技术运营中心","常驻城市":"广州","有无驾照":"是","开车意愿":"我可以做替补","带无人机":"木有无人机...","手机号":"","身份证号":"","去程航班":"广州8号出发-- CZ3477广州白云-林芝米林(07:05-11:00)","返程航班":"广州11号到达-- CZ3478林芝米林-广州白云(11:40-15:20)","室友意向":"无","车号":"8号车","游戏分组":"3","现场角色":"","重庆住宿(11.7)":"","索松村住宿(11.8)":"索松村桃花韵酒店 5号 正对双床5（室友：周啟彬）","巴松措住宿(11.9~10)":"巴松措纳拉尕布民宿 5号 三楼双床房（室友：周啟彬）","饮食忌口/过敏":"","高反情况":"","打呼噜":"","其他备注":""},{"_id":"fengyunrao","企微ID":"fengyunrao","中文名":"饶峰云","身份证姓名":"饶峰云","性别":"男","部门/中心":"多媒体技术中心","常驻城市":"北京","有无驾照":"是","开车意愿":"还是算了吧","带无人机":"木有无人机...","手机号":"","身份证号":"","去程航班":"广州8号出发-- CZ3477广州白云-林芝米林(07:05-11:00)","返程航班":"北京首都11号到达-- TV9984林芝米林-重庆江北(11:20-13:35) + CA1438 重庆江北-北京首都(15:55-18:30)","室友意向":"无","车号":"8号车","游戏分组":"3","现场角色":"","重庆住宿(11.7)":"","索松村住宿(11.8)":"索松村桃花韵酒店 14号 全景双床1（室友：马子扬）","巴松措住宿(11.9~10)":"巴松措纳拉尕布民宿 14号 二楼双床房（室友：马子扬）","饮食忌口/过敏":"","高反情况":"","打呼噜":"","其他备注":""},{"_id":"leiffyli","企微ID":"leiffyli","中文名":"李方源","身份证姓名":"李方源","性别":"男","部门/中心":"云平台技术运营中心","常驻城市":"广州","有无驾照":"是","开车意愿":"非常可以","带无人机":"可能会悄悄带，不太会玩，娱乐用的","手机号":"","身份证号":"","去程航班":"广州8号出发-- CZ3477广州白云-林芝米林(07:05-11:00)","返程航班":"广州11号到达-- CZ3478林芝米林-广州白云(11:40-15:20)","室友意向":"chenzzchen","车号":"9号车","游戏分组":"4","现场角色":"","重庆住宿(11.7)":"","索松村住宿(11.8)":"索松村桃花韵酒店 3号 正对双床3（室友：陈壮志）","巴松措住宿(11.9~10)":"巴松措纳拉尕布民宿 3号 三楼双床房（室友：陈壮志）","饮食忌口/过敏":"","高反情况":"","打呼噜":"","其他备注":""},{"_id":"sidneyzhou","企微ID":"sidneyzhou","中文名":"周煜","身份证姓名":"周煜","性别":"男","部门/中心":"多媒体技术中心","常驻城市":"深圳","有无驾照":"是","开车意愿":"非常可以","带无人机":"木有无人机...","手机号":"","身份证号":"","去程航班":"深圳7号出发-- ZH9469深圳宝安-重庆江北(20:15-22:40) + TV9983重庆江北-林芝米林(07:50-10:30)","返程航班":"深圳11号到达-- TV9984林芝米林-重庆江北(11:20-13:35) + CZ3456重庆江北-深圳宝安(15:35-17:55)","室友意向":"nobleqiao","车号":"9号车","游戏分组":"4","现场角色":"","重庆住宿(11.7)":"重庆诺富特酒店 6号（室友：文杰）","索松村住宿(11.8)":"索松村桃花韵酒店 11号 正对双床11（室友：乔宁博）","巴松措住宿(11.9~10)":"巴松措纳拉尕布民宿 11号 二楼双床房（室友：乔宁博）","饮食忌口/过敏":"","高反情况":"","打呼噜":"","其他备注":""},{"_id":"amyzhuang","企微ID":"amyzhuang","中文名":"庄少菀","身份证姓名":"庄少菀","性别":"女","部门/中心":"QA组","常驻城市":"广州","有无驾照":"否","开车意愿":"还是算了吧","带无人机":"木有无人机...","手机号":"","身份证号":"","去程航班":"广州8号出发-- CZ3477广州白云-林芝米林(07:05-11:00)","返程航班":"广州11号到达-- CZ3478林芝米林-广州白云(11:40-15:20)","室友意向":"candyxiong","车号":"9号车","游戏分组":"4","现场角色":"","重庆住宿(11.7)":"","索松村住宿(11.8)":"索松村桃花韵酒店 2号 正对双床2（室友：熊婷）","巴松措住宿(11.9~10)":"巴松措纳拉尕布民宿 2号 三楼双床房（室友：熊婷）","饮食忌口/过敏":"","高反情况":"","打呼噜":"","其他备注":""},{"_id":"candyxiong","企微ID":"candyxiong","中文名":"熊婷","身份证姓名":"熊婷","性别":"女","部门/中心":"测试中心","常驻城市":"深圳","有无驾照":"是","开车意愿":"还是算了吧","带无人机":"木有无人机...","手机号":"","身份证号":"","去程航班":"广州8号出发-- CZ3477广州白云-林芝米林(07:05-11:00)","返程航班":"深圳11号到达-- TV9984林芝米林-重庆江北(11:20-13:35) + CZ3456重庆江北-深圳宝安(15:35-17:55)","室友意向":"amyzhuang","车号":"9号车","游戏分组":"4","现场角色":"","重庆住宿(11.7)":"","索松村住宿(11.8)":"索松村桃花韵酒店 2号 正对双床2（室友：庄少菀）","巴松措住宿(11.9~10)":"巴松措纳拉尕布民宿 2号 三楼双床房（室友：庄少菀）","饮食忌口/过敏":"","高反情况":"","打呼噜":"","其他备注":""},{"_id":"botingwu","企微ID":"botingwu","中文名":"吴博婷","身份证姓名":"吴博婷","性别":"女","部门/中心":"云平台技术运营中心","常驻城市":"北京","有无驾照":"是","开车意愿":"非常可以","带无人机":"木有无人机...","手机号":"","身份证号":"","去程航班":"北京7号出发-- CA1449北京首都-重庆江北(18:45-22:05) + TV9983重庆江北-林芝米林(07:50-10:30)","返程航班":"北京首都11号到达-- TV9984林芝米林-重庆江北(11:20-13:35) + CA1438 重庆江北-北京首都(15:55-18:30)","室友意向":"ireneyan","车号":"10号车","游戏分组":"4","现场角色":"","重庆住宿(11.7)":"重庆诺富特酒店 7号（单人）","索松村住宿(11.8)":"索松村桃花韵酒店 1号 正对双床1（室友：颜秋宇）","巴松措住宿(11.9~10)":"巴松措纳拉尕布民宿 1号 三楼双床房（室友：颜秋宇）","饮食忌口/过敏":"","高反情况":"","打呼噜":"","其他备注":""},{"_id":"noahchen","企微ID":"noahchen","中文名":"陈培炫","身份证姓名":"陈培炫","性别":"男","部门/中心":"机器学习平台中心","常驻城市":"深圳","有无驾照":"是","开车意愿":"我可以做替补","带无人机":"木有无人机...","手机号":"","身份证号":"","去程航班":"深圳7号出发-- ZH9469深圳宝安-重庆江北(20:15-22:40) + TV9983重庆江北-林芝米林(07:50-10:30)","返程航班":"深圳11号到达-- TV9984林芝米林-重庆江北(11:20-13:35) + CZ3456重庆江北-深圳宝安(15:35-17:55)","室友意向":"无","车号":"10号车","游戏分组":"4","现场角色":"","重庆住宿(11.7)":"重庆诺富特酒店 5号（室友：乔宁博）","索松村住宿(11.8)":"索松村桃花韵酒店 10号 正对双床10（室友：黄皖湘）","巴松措住宿(11.9~10)":"巴松措纳拉尕布民宿 10号 二楼双床房（室友：黄皖湘）","饮食忌口/过敏":"","高反情况":"","打呼噜":"","其他备注":""},{"_id":"frankxia","企微ID":"frankxia","中文名":"夏凡","身份证姓名":"夏凡","性别":"男","部门/中心":"测试中心","常驻城市":"广州","有无驾照":"是","开车意愿":"我可以做替补","带无人机":"木有无人机...","手机号":"","身份证号":"","去程航班":"广州8号出发-- CZ3477广州白云-林芝米林(07:05-11:00)","返程航班":"广州11号到达-- CZ3478林芝米林-广州白云(11:40-15:20)","室友意向":"mattzheng","车号":"10号车","游戏分组":"4","现场角色":"","重庆住宿(11.7)":"","索松村住宿(11.8)":"索松村桃花韵酒店 4号 正对双床4（室友：郑海兵）","巴松措住宿(11.9~10)":"巴松措纳拉尕布民宿 4号 三楼双床房（室友：郑海兵）","饮食忌口/过敏":"","高反情况":"","打呼噜":"","其他备注":""},{"_id":"ireneyan","企微ID":"ireneyan","中文名":"颜秋宇","身份证姓名":"颜秋宇","性别":"女","部门/中心":"云平台技术运营中心","常驻城市":"广州","有无驾照":"否","开车意愿":"还是算了吧","带无人机":"木有无人机...","手机号":"","身份证号":"","去程航班":"广州8号出发-- CZ3477广州白云-林芝米林(07:05-11:00)","返程航班":"广州11号到达-- CZ3478林芝米林-广州白云(11:40-15:20)","室友意向":"botingwu","车号":"10号车","游戏分组":"4","现场角色":"","重庆住宿(11.7)":"","索松村住宿(11.8)":"索松村桃花韵酒店 1号 正对双床1（室友：吴博婷）","巴松措住宿(11.9~10)":"巴松措纳拉尕布民宿 1号 三楼双床房（室友：吴博婷）","饮食忌口/过敏":"","高反情况":"","打呼噜":"","其他备注":""},{"_id":"sarlmolchen","企微ID":"sarlmolchen","中文名":"陈国敏","身份证姓名":"陈国敏","性别":"男","部门/中心":"后台开发中心","常驻城市":"广州","有无驾照":"是","开车意愿":"非常可以","带无人机":"木有无人机...","手机号":"","身份证号":"","去程航班":"广州8号出发-- CZ3477广州白云-林芝米林(07:05-11:00)","返程航班":"广州11号到达-- CZ3478林芝米林-广州白云(11:40-15:20)","室友意向":"bierhuang","车号":"11号车","游戏分组":"5","现场角色":"","重庆住宿(11.7)":"","索松村住宿(11.8)":"索松村桃花韵酒店 6号 正对双床6（室友：黄清）","巴松措住宿(11.9~10)":"巴松措纳拉尕布民宿 6号 三楼双床房（室友：黄清）","饮食忌口/过敏":"","高反情况":"","打呼噜":"","其他备注":"无"},{"_id":"bojiehu","企微ID":"bojiehu","中文名":"胡博杰","身份证姓名":"胡博杰","性别":"男","部门/中心":"信息六组","常驻城市":"","有无驾照":"是","开车意愿":"我可以做替补","带无人机":"木有无人机...","手机号":"","身份证号":"","去程航班":"北京7号出发-- CA1449北京首都-重庆江北(18:45-22:05) + TV9983重庆江北-林芝米林(07:50-10:30)","返程航班":"北京首都11号到达-- TV9984林芝米林-重庆江北(11:20-13:35) + CA1438 重庆江北-北京首都(15:55-18:30)","室友意向":"无","车号":"11号车","游戏分组":"5","现场角色":"","重庆住宿(11.7)":"重庆诺富特酒店 4号（室友：庞永杰）","索松村住宿(11.8)":"索松村桃花韵酒店 15号 全景双床2（室友：叶泽雄）","巴松措住宿(11.9~10)":"巴松措纳拉尕布民宿 15号 二楼双床房（室友：叶泽雄）","饮食忌口/过敏":"","高反情况":"","打呼噜":"","其他备注":""},{"_id":"rockzheng","企微ID":"rockzheng","中文名":"郑建军","身份证姓名":"郑建军","性别":"男","部门/中心":"基础架构中心","常驻城市":"广州","有无驾照":"是","开车意愿":"还是算了吧","带无人机":"木有无人机...","手机号":"","身份证号":"","去程航班":"广州8号出发-- CZ3477广州白云-林芝米林(07:05-11:00)","返程航班":"广州11号到达-- CZ3478林芝米林-广州白云(11:40-15:20)","室友意向":"flashlin","车号":"11号车","游戏分组":"5","现场角色":"","重庆住宿(11.7)":"","索松村住宿(11.8)":"索松村桃花韵酒店 16号 全景双床3（室友：林枫）","巴松措住宿(11.9~10)":"巴松措纳拉尕布民宿 16号 二楼双床房（室友：林枫）","饮食忌口/过敏":"","高反情况":"","打呼噜":"","其他备注":""},{"_id":"zixiangzhao","企微ID":"zixiangzhao","中文名":"赵自翔","身份证姓名":"赵自翔","性别":"男","部门/中心":"信息一组","常驻城市":"","有无驾照":"否","开车意愿":"还是算了吧","带无人机":"木有无人机...","手机号":"","身份证号":"","去程航班":"广州8号出发-- CZ3477广州白云-林芝米林(07:05-11:00)","返程航班":"广州11号到达-- CZ3478林芝米林-广州白云(11:40-15:20)","室友意向":"chaselli","车号":"11号车","游戏分组":"5","现场角色":"","重庆住宿(11.7)":"","索松村住宿(11.8)":"索松村桃花韵酒店 7号 正对双床7（室友：李琛）","巴松措住宿(11.9~10)":"巴松措纳拉尕布民宿 7号 三楼双床房（室友：李琛）","饮食忌口/过敏":"","高反情况":"","打呼噜":"","其他备注":""},{"_id":"elonqi","企微ID":"elonqi","中文名":"祁麟","身份证姓名":"祁麟","性别":"男","部门/中心":"业务一组","常驻城市":"","有无驾照":"","开车意愿":"","带无人机":"","手机号":"","身份证号":"","去程航班":"广州8号出发-- CZ3477广州白云-林芝米林(07:05-11:00)","返程航班":"广州11号到达-- CZ3478林芝米林-广州白云(11:40-15:20)","室友意向":"jackliang","车号":"导游车 1号车","游戏分组":"5","现场角色":"","重庆住宿(11.7)":"","索松村住宿(11.8)":"索松村桃花韵酒店 13号 正对双床13（室友：梁焯佳）","巴松措住宿(11.9~10)":"巴松措纳拉尕布民宿 13号 二楼双床房（室友：梁焯佳）","饮食忌口/过敏":"","高反情况":"","打呼噜":"","其他备注":""}],"schedule":[{"week":"D1","date":"11月08日","title":"米林机场—佛掌沙丘—派镇吞白村—达林村—索松村","tip":"","items":[{"start":"07:50","end":"10:30","act":"TV9983 重庆江北-林芝米林(07:50-10:30)","trans":"飞机"},{"start":"07:05","end":"11:00","act":"CZ3477 广州白云-林芝米林(07:05-11:00)","trans":"飞机"},{"start":"11:00","end":"11:30","act":"接机，合影","trans":""},{"start":"11:30","end":"11:45","act":"林芝米林机场—希尔顿酒店","trans":"自驾（柏油路8KM）"},{"start":"11:45","end":"12:45","act":"希尔顿午餐","trans":""},{"start":"12:45","end":"13:45","act":"希尔顿酒店—佛掌沙丘","trans":"自驾（柏油路60KM）"},{"start":"13:45","end":"14:35","act":"佛掌沙丘游览、滑沙","trans":""},{"start":"14:35","end":"15:05","act":"佛掌沙丘—吞白村古茹寺","trans":"自驾（柏油路27KM）"},{"start":"15:05","end":"15:45","act":"吞白村古茹寺登高远眺南迦巴瓦","trans":""},{"start":"15:45","end":"16:30","act":"公尊德姆农庄观景（雅江沙滩拍照打卡）喝酥油茶","trans":""},{"start":"16:30","end":"17:00","act":"吞白村—达林村","trans":"自驾（柏油路13KM）"},{"start":"17:00","end":"17:30","act":"达林村青稞田野漫步看双雪山（南迦巴瓦、加拉白垒）","trans":""},{"start":"17:30","end":"18:00","act":"达林村—索松村桃花韵酒店","trans":"自驾（柏油路9KM）"},{"start":"18:00","end":"19:00","act":"索松村山谷秘境轻徒步，看南迦巴瓦日照金山","trans":""},{"start":"19:00","end":"19:30","act":"入住酒店 桃花韵","trans":""},{"start":"19:30","end":"20:30","act":"桃花韵酒店晚餐","trans":""},{"start":"20:30","end":"23:00","act":"索松村自由活动","trans":""}]},{"week":"D2","date":"11月09日","title":"索松村—尼洋河风光带—巴河镇—巴松措—新措","tip":"","items":[{"start":"07:30","end":"09:30","act":"桃花韵酒店早餐、退房","trans":""},{"start":"09:30","end":"11:00","act":"索松村—尼洋河风光带","trans":"自驾（柏油路62KM）"},{"start":"11:00","end":"11:50","act":"尼洋河湿地栈道轻徒步赏西藏江南秋色","trans":"徒步（栈道2KM）"},{"start":"11:50","end":"12:40","act":"尼洋河风光带—百巴服务区","trans":"自驾（柏油路83KM）"},{"start":"12:40","end":"12:50","act":"百巴服务区加油","trans":""},{"start":"12:50","end":"13:10","act":"百巴服务区—巴河镇巴蜀鱼村","trans":"自驾（柏油路26KM）"},{"start":"13:10","end":"14:00","act":"巴河镇巴蜀鱼村午餐","trans":""},{"start":"14:00","end":"14:30","act":"巴河镇—巴松措售票处","trans":"自驾（柏油路36KM）"},{"start":"14:30","end":"16:00","act":"松措售票处—新措","trans":"自驾（越野路39KM）"},{"start":"16:00","end":"17:00","act":"新措秘境秋色越野摩托游览","trans":"自驾越野摩托（土路8KM）"},{"start":"17:00","end":"18:00","act":"新措—结巴村 江湖菜·石锅野生菌","trans":"自驾（越野路30KM）"},{"start":"19:00","end":"20:00","act":"江湖菜·石锅野生菌晚餐（暂定）","trans":""},{"start":"20:00","end":"20:30","act":"入住巴松措 · 纳拉尕布酒店","trans":""},{"start":"20:30","end":"24:00","act":"自由活动","trans":""}]},{"week":"D3","date":"11月10日","title":"巴松措景区内","tip":"","items":[{"start":"07:30","end":"09:30","act":"纳拉尕布酒店早餐","trans":""},{"start":"09:30","end":"09:50","act":"纳拉尕布酒店——湖心岛停车场","trans":"自驾（柏油路8KM）"},{"start":"09:50","end":"11:50","act":"达切拉观景台、湖心岛及湖边栈道游览","trans":""},{"start":"11:50","end":"12:00","act":"湖心岛——结巴村 和川味轩餐厅","trans":"自驾（柏油路7KM）"},{"start":"12:00","end":"13:00","act":"结巴村和川味轩餐厅 午餐（暂定）","trans":""},{"start":"13:00","end":"13:20","act":"结巴村——遗忘码头（停车）收车钥匙","trans":"自驾（柏油路2KM）"},{"start":"13:20","end":"14:00","act":"帆船游巴松措（遗忘码头-求子洞）","trans":""},{"start":"14:00","end":"17:00","act":"巴松措秘境徒步（挂经幡、玛尼堆、大草甸摆拍）","trans":"徒步（森林8KM）"},{"start":"17:00","end":"17:30","act":"措高村——松赞巴松措林卡酒店","trans":"自驾（柏油路10KM）"},{"start":"18:30","end":"20:30","act":"松赞巴松措林卡酒店喜马拉雅餐厅晚宴（暂定）","trans":"见晚宴rundown"},{"start":"20:30","end":"22:00","act":"回纳拉尕布酒店自由活动","trans":""}]}],"notices":[{"title":"出发前必读·信息收集","content":"请于11.7前在小程序提交身份证号与往返航班，用于统一订票","time":"2025-11-01 10:00","author":"组织者","level":"重要"},{"title":"高原出行提醒","content":"林芝海拔约3000m，建议提前备好高反药物，避免剧烈运动","time":"2025-11-03 14:00","author":"组织者","level":"普通"}],"_ts":1784259796789}